scciclient/__init__.py
scciclient/irmc/__init__.py
scciclient/irmc/elcm.py
scciclient/irmc/ipmi.py
scciclient/irmc/scci.py
scciclient/irmc/snmp.py
scciclient/irmc/viom/__init__.py
scciclient/irmc/viom/client.py
scciclient/irmc/viom/elcm.py
scciclient/tests/__init__.py
scciclient/tests/irmc/__init__.py
scciclient/tests/irmc/test_elcm.py
scciclient/tests/irmc/test_ipmi.py
scciclient/tests/irmc/test_scci.py
scciclient/tests/irmc/test_snmp.py
scciclient/tests/irmc/fixtures/irmc_report_ng.xml
scciclient/tests/irmc/fixtures/irmc_report_ok.xml
scciclient/tests/irmc/viom/__init__.py
scciclient/tests/irmc/viom/test_client.py
scciclient/tests/irmc/viom/test_elcm.py
python_scciclient-0.17.0.dist-info/AUTHORS
python_scciclient-0.17.0.dist-info/LICENSE
python_scciclient-0.17.0.dist-info/METADATA
python_scciclient-0.17.0.dist-info/WHEEL
python_scciclient-0.17.0.dist-info/pbr.json
python_scciclient-0.17.0.dist-info/top_level.txt
python_scciclient-0.17.0.dist-info/RECORD
