Metadata-Version: 2.1
Name: python-scciclient
Version: 0.17.0
Summary: Python ServerView Common Command Interface (SCCI) Client Library
Home-page: https://opendev.org/x/python-scciclient
Author: FUJITSU LIMITED
Author-email: fj-lsoft-scciclient@dl.jp.fujitsu.com
Classifier: Development Status :: 4 - Beta
Classifier: Environment :: Console
Classifier: Environment :: OpenStack
Classifier: Intended Audience :: Information Technology
Classifier: Intended Audience :: System Administrators
Classifier: License :: OSI Approved :: Apache Software License
Classifier: Operating System :: POSIX :: Linux
Classifier: Programming Language :: Python
Classifier: Programming Language :: Python :: 3
Requires-Python: >=3.8
License-File: LICENSE
License-File: AUTHORS
Requires-Dist: pbr !=2.1.0,>=2.0.0
Requires-Dist: Babel !=2.4.0,>=2.3.4
Requires-Dist: pyghmi >=1.0.24
Requires-Dist: pysnmp-lextudio >=5.0.0
Requires-Dist: pyasn1 >=0.5.1
Requires-Dist: pyasn1-modules >=0.3.0
Requires-Dist: requests >=2.14.2
Requires-Dist: defusedxml >=0.7.0
Requires-Dist: oslo.utils >=3.33.0
Requires-Dist: oslo.serialization !=2.19.1,>=2.18.0
